{
  "hash": "f6fa7582",
  "configHash": "2170d083",
  "lockfileHash": "d73f4451",
  "browserHash": "d785f368",
  "optimized": {
    "react": {
      "src": "../../node_modules/react/index.js",
      "file": "react.js",
      "fileHash": "fbdc0df6",
      "needsInterop": true
    },
    "react-dom/client": {
      "src": "../../node_modules/react-dom/client.js",
      "file": "react-dom_client.js",
      "fileHash": "18b22f9c",
      "needsInterop": true
    },
    "react-router-dom": {
      "src": "../../node_modules/react-router-dom/dist/index.js",
      "file": "react-router-dom.js",
      "fileHash": "63f6fdbc",
      "needsInterop": false
    },
    "formik": {
      "src": "../../node_modules/formik/dist/formik.esm.js",
      "file": "formik.js",
      "fileHash": "15554ff5",
      "needsInterop": false
    },
    "axios": {
      "src": "../../node_modules/axios/index.js",
      "file": "axios.js",
      "fileHash": "f389ffb0",
      "needsInterop": false
    }
  },
  "chunks": {
    "chunk-TNTPHDQH": {
      "file": "chunk-TNTPHDQH.js"
    },
    "chunk-32E4H3EV": {
      "file": "chunk-32E4H3EV.js"
    },
    "chunk-G3PMV62Z": {
      "file": "chunk-G3PMV62Z.js"
    }
  }
}